animu/__init__.py
animu/client.py
animu/model.py
animu/roleplay.py
animu-0.2.0.dist-info/LICENSE
animu-0.2.0.dist-info/METADATA
animu-0.2.0.dist-info/WHEEL
animu-0.2.0.dist-info/top_level.txt
animu-0.2.0.dist-info/RECORD
