Metadata-Version: 2.1
Name: animu
Version: 0.2.0
Summary: Animu API Wrapper written in Python that has both Sync & Async Client
Home-page: http://github.com/EitoZX/Animu
Author: EitoZX (Eito)
Author-email: iameitozx@gmail.com
Keywords: animu-api,anime,anime-quotes,anime-api,animeapi,animu,anime-quotes-api
Requires-Dist: aiohttp
Requires-Dist: requests
